FogifySDK/FogifySDK.py
FogifySDK/__init__.py
FogifySDK/tests/__init__.py
FogifySDK/tests/tests.py
FogifySDK-0.0.3.dist-info/METADATA
FogifySDK-0.0.3.dist-info/WHEEL
FogifySDK-0.0.3.dist-info/top_level.txt
FogifySDK-0.0.3.dist-info/RECORD
