Metadata-Version: 2.1
Name: FogifySDK
Version: 0.0.3
Summary: The fogify's SDK library
Author: Moysis Symeonides
Author-email: symeonidis.moysis@cs.ucy.ac.cy
License: UNKNOWN
Platform: UNKNOWN
Requires-Python: >=3.5
